dagster_iceberg/__init__.py
dagster_iceberg/config.py
dagster_iceberg/handler.py
dagster_iceberg/py.typed
dagster_iceberg/resource.py
dagster_iceberg/version.py
dagster_iceberg/_db_io_manager/__init__.py
dagster_iceberg/_db_io_manager/io_manager.py
dagster_iceberg/_db_io_manager/utils.py
dagster_iceberg/_utils/__init__.py
dagster_iceberg/_utils/io.py
dagster_iceberg/_utils/partitions.py
dagster_iceberg/_utils/properties.py
dagster_iceberg/_utils/retries.py
dagster_iceberg/_utils/schema.py
dagster_iceberg/_utils/transforms.py
dagster_iceberg/_utils/warnings.py
dagster_iceberg/io_manager/__init__.py
dagster_iceberg/io_manager/arrow.py
dagster_iceberg/io_manager/base.py
dagster_iceberg/io_manager/daft.py
dagster_iceberg/io_manager/pandas.py
dagster_iceberg/io_manager/polars.py
dagster_iceberg/io_manager/spark.py
dagster_iceberg-0.3.7.dist-info/METADATA
dagster_iceberg-0.3.7.dist-info/WHEEL
dagster_iceberg-0.3.7.dist-info/RECORD
